{
	"gboolean": "boolean",
	"gint": "number",
	"guint": "number",
	"gint8": "number",
	"guint8": "number",
	"gint16": "number",
	"guint16": "number",
	"gint32": "number",
	"guint32": "number",
	"gint64": "number",
	"guint64": "number",
	"glong": "number",
	"gulong": "number",
	"gshort": "number",
	"gushort": "number",
	"gsize": "number",
	"gssize": "number",
	"gdouble": "number",
	"gfloat": "number",
	"utf8": "string",
	"filename": "string",
	"gpointer": "External",
	"none": "void",
	"GLib.Quark": "number",
	"GLib.Bytes": "External",
	"GLib.HashTable": "External",
	"GLib.KeyFile": "External",
	"GLib.Variant": "External",
	"GLib.List": "External",
	"GLib.PtrArray": "External",
	"GLib.Strv": "External"
}
